Real Traffic Light Controller/Traffic_Light_Controller.v

module trafficLightController (clk , reset, sensor, mainStreetLights, sideStreetLights);

parameter S0 = 3'b000,
		  S1 = 3'b001,
		  S2 = 3'b010,
		  S3 = 3'b011,
		  S4 = 3'b100,
		  S5 = 3'b101,
	      S6 = 3'b110;

parameter mainStreetGREENtimer = 4'd10, //10 Seconds
	      mainStreetYELLOWtimer = 4'd3, //3 Seconds
	      mainStreetREDtimer = 4'd1, //1 Seconds
	      sideStreetGREENtimer = 4'd10, // 10 Seconds
	      sideStreetYELLOWtimer = 4'd3, // 3 Seconds
	      sideStreetREDtimer = 4'd2; // 1 Seconds

input clk,reset,sensor;
output reg [2:0] mainStreetLights, sideStreetLights;

reg [2:0] State;
reg [3:0] counter;


always @(*)
	begin
		case(State)
			S0: 
			begin
				mainStreetLights = 3'b100;
				sideStreetLights = 3'b100; // mainStreet_RED ON, sideStreet_RED ON  Reset State.
			end
			S1:
			begin
				mainStreetLights = 3'b001;
				sideStreetLights = 3'b100; // mainStreet_GREEN ON, sideStreet_RED ON Default State or if sensor = 1 Keep ON for 10 seconds
			end
			S2:
			begin
				mainStreetLights = 3'b010;
				sideStreetLights = 3'b100; // mainStreet_YELLOW ON, sideStreet_RED ON , Keep ON for 3 seconds
			end
			S3:
			begin
				mainStreetLights = 3'b100;
				sideStreetLights = 3'b100; // mainStreet_RED ON, sideStreet_RED ON , Keep ON for 2 sec
			end
  			S4:
			begin
				mainStreetLights = 3'b100;
				sideStreetLights = 3'b001; // mainStreet_RED ON, sideStreet_GREEN ON , Keep ON for 10 sec
			end
			S5:
			begin
				mainStreetLights = 3'b100;
				sideStreetLights = 3'b010; //  mainStreet_RED ON, sideStreet_YELLOW ON, Keep On for 3 sec;
			end
			S6:
			begin
				mainStreetLights = 3'b100;
				sideStreetLights = 3'b100; //  mainStreet_RED ON, sideStreet_RED ON, Keep On for 1 sec;
			end
			default:
			begin
				mainStreetLights = 3'b001;
				sideStreetLights = 3'b100; // mainStreet_GREEN ON, sideStreet_RED ON Default State or if sensor = 1 Keep ON for 10 seconds
			end

		endcase
	end

always @(posedge clk or posedge reset)
	begin
		if (reset)
		begin
			State <= S0;
			counter <= 0;
		end
		else if (reset == 0 && sensor == 0) //default State
		begin
			State <= S1;
			counter <= 0;    
		end
		else if (reset == 0 && sensor == 1)
		begin
			case (State)
				S1:
					if (counter < mainStreetGREENtimer)
					begin
						State <= S1;
						counter <= counter + 1;
					end
					else
					begin	
						State <= S2;
						counter <= 0;
					end
				S2:
					if (counter < mainStreetYELLOWtimer)
					begin
						State <= S2;
						counter <= counter + 1;
					end
					else
					begin
						State <= S3;
						counter <= 0;
					end
				S3:
					if (counter < mainStreetREDtimer)
					begin
						State <= S3;
						counter <= counter + 1;
					end
					else
					begin
						State <= S4;
						counter <= 0;
					end
				S4:
					if (counter < sideStreetGREENtimer)
					begin
						State <= S4;
						counter <= counter + 1;
					end
					else
					begin
						State <= S5;
						counter <= 0;
					end
				S5:
					if (counter < sideStreetYELLOWtimer)
					begin
						State <= S5;
						counter <=counter+1;
					end
					else 
					begin
						State <= S6;
						counter <= 0;
					end
				S6:
					if (counter < sideStreetREDtimer)
					begin
						State <= S6;
						counter <= counter + 1;
					end
					else
					begin
						State <= S1;
						counter <= 0;
					end
				default: State <= S1;
			endcase
		end
	end
endmodule

Real Traffic Light Controller/clock_Divider.v

module Clock_divider(clock_in, reset, clock_out );

input clock_in, reset; // input clock on FPGA
output clock_out; // output clock after dividing the input clock by divisor

reg[27:0] counter= 28'd0;
parameter DIVISOR = 28'd2;// The frequency of the output clk_out  = The frequency of the input clk_in divided by DIVISOR
			  // For example: Fclk_in = 50Mhz, if you want to get 1Hz signal to blink LEDs
			  // You will modify the DIVISOR parameter value to 28'd50.000.000
			  // Then the frequency of the output clk_out = 50Mhz/50.000.000 = 1Hz
always @(posedge clock_in)
begin
	if (reset)
	begin
		counter <= 28'd0;
	end
	else 
	begin
		 counter <= counter + 28'd1;
		 if(counter>=(DIVISOR-1))
		 	begin
 				counter <= 28'd0;
			end
	end
end
assign clock_out = (counter<DIVISOR/2)?1'b0:1'b1; // duty cycle
endmodule

Real Traffic Light Controller/Traffic_Light_top.v

module TrafficLightTop (masterclk , reset_button, sensor_button, mainStreetleds, sideStreetleds); // for interfacing with the FPGA

input masterclk, reset_button, sensor_button;
output [2:0]mainStreetleds, sideStreetleds;

wire dividedclk;

	Clock_divider CLK (.clock_in(masterclk) , .reset(reset_button), .clock_out(dividedclk));
	trafficLightController TLC (.clk(dividedclk), .reset(reset_button), .sensor(sensor_button), .mainStreetLights(mainStreetleds), .sideStreetLights(sideStreetleds));


endmodule

Real Traffic Light Controller/TLCTestBench.v
`timescale 1ns / 1ps

module Traffic_Light_Controller_TestBench ();

reg masterclk, reset_button, sensor_button;
wire [2:0] mainStreetleds, sideStreetleds;

	TrafficLightTop DUT (.masterclk(masterclk), .reset_button(reset_button), .sensor_button(sensor_button), .mainStreetleds(mainStreetleds), .sideStreetleds(sideStreetleds));
	
	initial
	begin
		$monitor($time," MAIN STREET RED = %b, MAIN STREET YELLOW = %b, MAIN STREET GREEN =%b, SIDE STREET RED = %b, SIDE STREET YELLOW = %b, SIDE STREET GREEN = %b ", mainStreetleds[2], mainStreetleds[1], mainStreetleds[0], sideStreetleds[2], sideStreetleds[1], sideStreetleds[0]);
		$dumpfile("TrafficLightwaveform.vcd");
		$dumpvars(0, Traffic_Light_Controller_TestBench);
	end
	
	task initialize;
		begin
			reset_button = 0;
			sensor_button = 0;
			masterclk = 0;

		end
	endtask

	always
	begin
	        #10  masterclk = ~ masterclk;
	end
	
	initial
	begin
		initialize;
		@(negedge masterclk)
			   sensor_button = 1;
		@(negedge masterclk)
	    	#1500 sensor_button = 0;
	    @(negedge masterclk)
	    	#500 reset_button = 1;	sensor_button = 0;
	    #2000 $finish;
	end
	
endmodule

Real Traffic Light Controller/TrafficLightwaveform.vcd
$date
	Tue Jun 23 02:47:11 2020
$end
$version
	Icarus Verilog
$end
$timescale
	1ps
$end
$scope module Traffic_Light_Controller_TestBench $end
$var wire 3 ! mainStreetleds [2:0] $end
$var wire 3 " sideStreetleds [2:0] $end
$var reg 1 # masterclk $end
$var reg 1 $ reset_button $end
$var reg 1 % sensor_button $end
$scope module DUT $end
$var wire 1 & dividedclk $end
$var wire 3 ' mainStreetleds [2:0] $end
$var wire 1 ( masterclk $end
$var wire 1 ) reset_button $end
$var wire 1 * sensor_button $end
$var wire 3 + sideStreetleds [2:0] $end
$scope module CLK $end
$var wire 1 ( clock_in $end
$var wire 1 & clock_out $end
$var wire 1 ) reset $end
$var reg 28 , counter [27:0] $end
$upscope $end
$scope module TLC $end
$var wire 1 & clk $end
$var wire 1 ) reset $end
$var wire 1 * sensor $end
$var reg 3 - State [2:0] $end
$var reg 4 . counter [3:0] $end
$var reg 3 / mainStreetLights [2:0] $end
$var reg 3 0 sideStreetLights [2:0] $end
$upscope $end
$upscope $end
$scope task initialize $end
$upscope $end
$upscope $end
$enddefinitions $end
#0
$dumpvars
bx 0
bx /
bx .
bx -
b0 ,
bx +
0*
0)
0(
bx '
0&
0%
0$
0#
bx "
bx !
$end
#10000
b100 0
b100 "
b100 +
b1 /
b1 !
b1 '
b0 .
b1 -
1&
b1 ,
1#
1(
#20000
1%
1*
0#
0(
#30000
0&
b0 ,
1#
1(
#40000
0#
0(
#50000
b1 .
1&
b1 ,
1#
1(
#60000
0#
0(
#70000
0&
b0 ,
1#
1(
#80000
0#
0(
#90000
b10 .
1&
b1 ,
1#
1(
#100000
0#
0(
#110000
0&
b0 ,
1#
1(
#120000
0#
0(
#130000
b11 .
1&
b1 ,
1#
1(
#140000
0#
0(
#150000
0&
b0 ,
1#
1(
#160000
0#
0(
#170000
b100 .
1&
b1 ,
1#
1(
#180000
0#
0(
#190000
0&
b0 ,
1#
1(
#200000
0#
0(
#210000
b101 .
1&
b1 ,
1#
1(
#220000
0#
0(
#230000
0&
b0 ,
1#
1(
#240000
0#
0(
#250000
b110 .
1&
b1 ,
1#
1(
#260000
0#
0(
#270000
0&
b0 ,
1#
1(
#280000
0#
0(
#290000
b111 .
1&
b1 ,
1#
1(
#300000
0#
0(
#310000
0&
b0 ,
1#
1(
#320000
0#
0(
#330000
b1000 .
1&
b1 ,
1#
1(
#340000
0#
0(
#350000
0&
b0 ,
1#
1(
#360000
0#
0(
#370000
b1001 .
1&
b1 ,
1#
1(
#380000
0#
0(
#390000
0&
b0 ,
1#
1(
#400000
0#
0(
#410000
b1010 .
1&
b1 ,
1#
1(
#420000
0#
0(
#430000
0&
b0 ,
1#
1(
#440000
0#
0(
#450000
b10 /
b10 !
b10 '
b0 .
b10 -
1&
b1 ,
1#
1(
#460000
0#
0(
#470000
0&
b0 ,
1#
1(
#480000
0#
0(
#490000
b1 .
1&
b1 ,
1#
1(
#500000
0#
0(
#510000
0&
b0 ,
1#
1(
#520000
0#
0(
#530000
b10 .
1&
b1 ,
1#
1(
#540000
0#
0(
#550000
0&
b0 ,
1#
1(
#560000
0#
0(
#570000
b11 .
1&
b1 ,
1#
1(
#580000
0#
0(
#590000
0&
b0 ,
1#
1(
#600000
0#
0(
#610000
b100 /
b100 !
b100 '
b0 .
b11 -
1&
b1 ,
1#
1(
#620000
0#
0(
#630000
0&
b0 ,
1#
1(
#640000
0#
0(
#650000
b1 .
1&
b1 ,
1#
1(
#660000
0#
0(
#670000
0&
b0 ,
1#
1(
#680000
0#
0(
#690000
b1 0
b1 "
b1 +
b0 .
b100 -
1&
b1 ,
1#
1(
#700000
0#
0(
#710000
0&
b0 ,
1#
1(
#720000
0#
0(
#730000
b1 .
1&
b1 ,
1#
1(
#740000
0#
0(
#750000
0&
b0 ,
1#
1(
#760000
0#
0(
#770000
b10 .
1&
b1 ,
1#
1(
#780000
0#
0(
#790000
0&
b0 ,
1#
1(
#800000
0#
0(
#810000
b11 .
1&
b1 ,
1#
1(
#820000
0#
0(
#830000
0&
b0 ,
1#
1(
#840000
0#
0(
#850000
b100 .
1&
b1 ,
1#
1(
#860000
0#
0(
#870000
0&
b0 ,
1#
1(
#880000
0#
0(
#890000
b101 .
1&
b1 ,
1#
1(
#900000
0#
0(
#910000
0&
b0 ,
1#
1(
#920000
0#
0(
#930000
b110 .
1&
b1 ,
1#
1(
#940000
0#
0(
#950000
0&
b0 ,
1#
1(
#960000
0#
0(
#970000
b111 .
1&
b1 ,
1#
1(
#980000
0#
0(
#990000
0&
b0 ,
1#
1(
#1000000
0#
0(
#1010000
b1000 .
1&
b1 ,
1#
1(
#1020000
0#
0(
#1030000
0&
b0 ,
1#
1(
#1040000
0#
0(
#1050000
b1001 .
1&
b1 ,
1#
1(
#1060000
0#
0(
#1070000
0&
b0 ,
1#
1(
#1080000
0#
0(
#1090000
b1010 .
1&
b1 ,
1#
1(
#1100000
0#
0(
#1110000
0&
b0 ,
1#
1(
#1120000
0#
0(
#1130000
b10 0
b10 "
b10 +
b0 .
b101 -
1&
b1 ,
1#
1(
#1140000
0#
0(
#1150000
0&
b0 ,
1#
1(
#1160000
0#
0(
#1170000
b1 .
1&
b1 ,
1#
1(
#1180000
0#
0(
#1190000
0&
b0 ,
1#
1(
#1200000
0#
0(
#1210000
b10 .
1&
b1 ,
1#
1(
#1220000
0#
0(
#1230000
0&
b0 ,
1#
1(
#1240000
0#
0(
#1250000
b11 .
1&
b1 ,
1#
1(
#1260000
0#
0(
#1270000
0&
b0 ,
1#
1(
#1280000
0#
0(
#1290000
b100 0
b100 "
b100 +
b0 .
b110 -
1&
b1 ,
1#
1(
#1300000
0#
0(
#1310000
0&
b0 ,
1#
1(
#1320000
0#
0(
#1330000
b1 .
1&
b1 ,
1#
1(
#1340000
0#
0(
#1350000
0&
b0 ,
1#
1(
#1360000
0#
0(
#1370000
b10 .
1&
b1 ,
1#
1(
#1380000
0#
0(
#1390000
0&
b0 ,
1#
1(
#1400000
0#
0(
#1410000
b1 /
b1 !
b1 '
b0 .
b1 -
1&
b1 ,
1#
1(
#1420000
0#
0(
#1430000
0&
b0 ,
1#
1(
#1440000
0#
0(
#1450000
b1 .
1&
b1 ,
1#
1(
#1460000
0#
0(
#1470000
0&
b0 ,
1#
1(
#1480000
0#
0(
#1490000
b10 .
1&
b1 ,
1#
1(
#1500000
0#
0(
#1510000
0&
b0 ,
1#
1(
#1520000
0#
0(
#1530000
b11 .
1&
b1 ,
1#
1(
#1540000
0#
0(
0%
0*
#1550000
0&
b0 ,
1#
1(
#1560000
0#
0(
#1570000
b0 .
1&
b1 ,
1#
1(
#1580000
0#
0(
#1590000
0&
b0 ,
1#
1(
#1600000
0#
0(
#1610000
1&
b1 ,
1#
1(
#1620000
0#
0(
#1630000
0&
b0 ,
1#
1(
#1640000
0#
0(
#1650000
1&
b1 ,
1#
1(
#1660000
0#
0(
#1670000
0&
b0 ,
1#
1(
#1680000
0#
0(
#1690000
1&
b1 ,
1#
1(
#1700000
0#
0(
#1710000
0&
b0 ,
1#
1(
#1720000
0#
0(
#1730000
1&
b1 ,
1#
1(
#1740000
0#
0(
#1750000
0&
b0 ,
1#
1(
#1760000
0#
0(
#1770000
1&
b1 ,
1#
1(
#1780000
0#
0(
#1790000
0&
b0 ,
1#
1(
#1800000
0#
0(
#1810000
1&
b1 ,
1#
1(
#1820000
0#
0(
#1830000
0&
b0 ,
1#
1(
#1840000
0#
0(
#1850000
1&
b1 ,
1#
1(
#1860000
0#
0(
#1870000
0&
b0 ,
1#
1(
#1880000
0#
0(
#1890000
1&
b1 ,
1#
1(
#1900000
0#
0(
#1910000
0&
b0 ,
1#
1(
#1920000
0#
0(
#1930000
1&
b1 ,
1#
1(
#1940000
0#
0(
#1950000
0&
b0 ,
1#
1(
#1960000
0#
0(
#1970000
1&
b1 ,
1#
1(
#1980000
0#
0(
#1990000
0&
b0 ,
1#
1(
#2000000
0#
0(
#2010000
1&
b1 ,
1#
1(
#2020000
0#
0(
#2030000
0&
b0 ,
1#
1(
#2040000
b100 /
b100 !
b100 '
b0 -
0#
0(
1$
1)
